{
    "Adana": {
        "degisiklik_90gun": 20079,
        "son_guncelleme": "2026-06-28 07:33:48"
    },
    "Adıyaman": {
        "degisiklik_90gun": 1631,
        "son_guncelleme": "2026-06-28 07:34:50"
    },
    "Afyonkarahisar": {
        "degisiklik_90gun": 18060,
        "son_guncelleme": "2026-06-28 07:35:21"
    },
    "Ağrı": {
        "degisiklik_90gun": 99,
        "son_guncelleme": "2026-06-28 07:35:39"
    },
    "Amasya": {
        "degisiklik_90gun": 1779,
        "son_guncelleme": "2026-06-28 07:36:00"
    },
    "Ankara": {
        "degisiklik_90gun": 202201,
        "son_guncelleme": "2026-06-28 07:36:31"
    },
    "Antalya": {
        "degisiklik_90gun": 101565,
        "son_guncelleme": "2026-06-28 07:36:57"
    },
    "Artvin": {
        "degisiklik_90gun": 1855,
        "son_guncelleme": "2026-06-28 07:38:03"
    },
    "Aydın": {
        "degisiklik_90gun": 5205,
        "son_guncelleme": "2026-06-28 07:38:25"
    },
    "Balıkesir": {
        "degisiklik_90gun": 75799,
        "son_guncelleme": "2026-06-28 07:38:51"
    },
    "Bilecik": {
        "degisiklik_90gun": 3377,
        "son_guncelleme": "2026-06-28 07:39:11"
    },
    "Bingöl": {
        "degisiklik_90gun": 542,
        "son_guncelleme": "2026-06-28 07:39:28"
    },
    "Bitlis": {
        "degisiklik_90gun": 370,
        "son_guncelleme": "2026-06-28 07:39:46"
    },
    "Bolu": {
        "degisiklik_90gun": 6086,
        "son_guncelleme": "2026-06-28 07:40:15"
    },
    "Burdur": {
        "degisiklik_90gun": 1297,
        "son_guncelleme": "2026-06-28 07:40:35"
    },
    "Bursa": {
        "degisiklik_90gun": 40248,
        "son_guncelleme": "2026-06-28 07:41:48"
    },
    "Çanakkale": {
        "degisiklik_90gun": 45300,
        "son_guncelleme": "2026-06-28 07:42:14"
    },
    "Çankırı": {
        "degisiklik_90gun": 3376,
        "son_guncelleme": "2026-06-28 07:42:37"
    },
    "Çorum": {
        "degisiklik_90gun": 5750,
        "son_guncelleme": "2026-06-28 07:42:58"
    },
    "Denizli": {
        "degisiklik_90gun": 8271,
        "son_guncelleme": "2026-06-28 07:44:09"
    },
    "Diyarbakır": {
        "degisiklik_90gun": 10523,
        "son_guncelleme": "2026-06-28 07:44:31"
    },
    "Edirne": {
        "degisiklik_90gun": 10310,
        "son_guncelleme": "2026-06-28 07:44:59"
    },
    "Elâzığ": {
        "degisiklik_90gun": 1823,
        "son_guncelleme": "2026-06-28 07:45:23"
    },
    "Erzincan": {
        "degisiklik_90gun": 1198,
        "son_guncelleme": "2026-06-28 07:45:51"
    },
    "Erzurum": {
        "degisiklik_90gun": 4082,
        "son_guncelleme": "2026-06-28 07:46:12"
    },
    "Eskişehir": {
        "degisiklik_90gun": 23529,
        "son_guncelleme": "2026-06-28 07:46:33"
    },
    "Gaziantep": {
        "degisiklik_90gun": 4121,
        "son_guncelleme": "2026-06-28 07:47:40"
    },
    "Giresun": {
        "degisiklik_90gun": 1920,
        "son_guncelleme": "2026-06-28 07:48:00"
    },
    "Gümüşhane": {
        "degisiklik_90gun": 702,
        "son_guncelleme": "2026-06-28 07:48:19"
    },
    "Hakkâri": {
        "degisiklik_90gun": 1316,
        "son_guncelleme": "2026-06-28 07:48:41"
    },
    "Hatay": {
        "degisiklik_90gun": 7505,
        "son_guncelleme": "2026-06-28 07:49:38"
    },
    "Isparta": {
        "degisiklik_90gun": 11763,
        "son_guncelleme": "2026-06-28 07:49:58"
    },
    "Mersin": {
        "degisiklik_90gun": 12676,
        "son_guncelleme": "2026-06-28 07:50:21"
    },
    "İstanbul": {
        "degisiklik_90gun": 372490,
        "son_guncelleme": "2026-06-28 07:51:04"
    },
    "İzmir": {
        "degisiklik_90gun": 160508,
        "son_guncelleme": "2026-06-28 07:51:40"
    },
    "Kars": {
        "degisiklik_90gun": 10177,
        "son_guncelleme": "2026-06-28 07:52:09"
    },
    "Kastamonu": {
        "degisiklik_90gun": 24774,
        "son_guncelleme": "2026-06-28 07:53:10"
    },
    "Kayseri": {
        "degisiklik_90gun": 137607,
        "son_guncelleme": "2026-06-28 07:53:52"
    },
    "Kırklareli": {
        "degisiklik_90gun": 44821,
        "son_guncelleme": "2026-06-28 07:54:16"
    },
    "Kırşehir": {
        "degisiklik_90gun": 1386,
        "son_guncelleme": "2026-06-28 07:54:33"
    },
    "Kocaeli": {
        "degisiklik_90gun": 15568,
        "son_guncelleme": "2026-06-28 07:54:58"
    },
    "Konya": {
        "degisiklik_90gun": 24401,
        "son_guncelleme": "2026-06-28 07:55:24"
    },
    "Kütahya": {
        "degisiklik_90gun": 10489,
        "son_guncelleme": "2026-06-28 07:55:48"
    },
    "Malatya": {
        "degisiklik_90gun": 37094,
        "son_guncelleme": "2026-06-28 07:56:12"
    },
    "Manisa": {
        "degisiklik_90gun": 19552,
        "son_guncelleme": "2026-06-28 07:56:41"
    },
    "Kahramanmaraş": {
        "degisiklik_90gun": 14650,
        "son_guncelleme": "2026-06-28 07:57:07"
    },
    "Mardin": {
        "degisiklik_90gun": 3185,
        "son_guncelleme": "2026-06-28 07:57:31"
    },
    "Muğla": {
        "degisiklik_90gun": 27944,
        "son_guncelleme": "2026-06-28 07:57:55"
    },
    "Muş": {
        "degisiklik_90gun": 1338,
        "son_guncelleme": "2026-06-28 07:58:13"
    },
    "Nevşehir": {
        "degisiklik_90gun": 3660,
        "son_guncelleme": "2026-06-28 07:58:34"
    },
    "Niğde": {
        "degisiklik_90gun": 2092,
        "son_guncelleme": "2026-06-28 07:58:59"
    },
    "Ordu": {
        "degisiklik_90gun": 2614,
        "son_guncelleme": "2026-06-28 07:59:25"
    },
    "Rize": {
        "degisiklik_90gun": 1098,
        "son_guncelleme": "2026-06-28 07:59:46"
    },
    "Sakarya": {
        "degisiklik_90gun": 8603,
        "son_guncelleme": "2026-06-28 08:00:33"
    },
    "Samsun": {
        "degisiklik_90gun": 3117,
        "son_guncelleme": "2026-06-28 08:00:59"
    },
    "Siirt": {
        "degisiklik_90gun": 670,
        "son_guncelleme": "2026-06-28 08:01:17"
    },
    "Sinop": {
        "degisiklik_90gun": 6725,
        "son_guncelleme": "2026-06-28 08:01:36"
    },
    "Sivas": {
        "degisiklik_90gun": 4155,
        "son_guncelleme": "2026-06-28 08:02:03"
    },
    "Tekirdağ": {
        "degisiklik_90gun": 39075,
        "son_guncelleme": "2026-06-28 08:02:32"
    },
    "Tokat": {
        "degisiklik_90gun": 6537,
        "son_guncelleme": "2026-06-28 08:03:08"
    },
    "Trabzon": {
        "degisiklik_90gun": 585,
        "son_guncelleme": "2026-06-28 08:03:40"
    },
    "Tunceli": {
        "degisiklik_90gun": 1328,
        "son_guncelleme": "2026-06-28 08:03:59"
    },
    "Şanlıurfa": {
        "degisiklik_90gun": 2929,
        "son_guncelleme": "2026-06-28 08:04:21"
    },
    "Uşak": {
        "degisiklik_90gun": 6693,
        "son_guncelleme": "2026-06-28 08:04:46"
    },
    "Van": {
        "degisiklik_90gun": 2158,
        "son_guncelleme": "2026-06-28 08:05:24"
    },
    "Yozgat": {
        "degisiklik_90gun": 5154,
        "son_guncelleme": "2026-06-28 08:06:02"
    },
    "Zonguldak": {
        "degisiklik_90gun": 14610,
        "son_guncelleme": "2026-06-28 08:06:20"
    },
    "Aksaray": {
        "degisiklik_90gun": 2029,
        "son_guncelleme": "2026-06-28 08:06:38"
    },
    "Bayburt": {
        "degisiklik_90gun": 750,
        "son_guncelleme": "2026-06-28 08:07:06"
    },
    "Karaman": {
        "degisiklik_90gun": 20295,
        "son_guncelleme": "2026-06-28 08:07:24"
    },
    "Kırıkkale": {
        "degisiklik_90gun": 12572,
        "son_guncelleme": "2026-06-28 08:07:42"
    },
    "Batman": {
        "degisiklik_90gun": 7563,
        "son_guncelleme": "2026-06-28 08:08:07"
    },
    "Şırnak": {
        "degisiklik_90gun": 3143,
        "son_guncelleme": "2026-06-28 08:08:31"
    },
    "Bartın": {
        "degisiklik_90gun": 1363,
        "son_guncelleme": "2026-06-28 08:08:48"
    },
    "Ardahan": {
        "degisiklik_90gun": 1735,
        "son_guncelleme": "2026-06-28 08:09:07"
    },
    "Iğdır": {
        "degisiklik_90gun": 1353,
        "son_guncelleme": "2026-06-28 08:09:33"
    },
    "Yalova": {
        "degisiklik_90gun": 671,
        "son_guncelleme": "2026-06-28 08:09:52"
    },
    "Karabük": {
        "degisiklik_90gun": 18996,
        "son_guncelleme": "2026-06-28 08:10:54"
    },
    "Kilis": {
        "degisiklik_90gun": 3571,
        "son_guncelleme": "2026-06-28 08:11:25"
    },
    "Osmaniye": {
        "degisiklik_90gun": 1068,
        "son_guncelleme": "2026-06-28 08:11:47"
    },
    "Düzce": {
        "degisiklik_90gun": 15323,
        "son_guncelleme": "2026-06-28 08:12:12"
    }
}